lahman/__init__.py
lahman/_fetch_data.py
lahman/data/_source.zip
lahman-0.0.1.dist-info/LICENSE
lahman-0.0.1.dist-info/METADATA
lahman-0.0.1.dist-info/WHEEL
lahman-0.0.1.dist-info/top_level.txt
lahman-0.0.1.dist-info/RECORD
