Metadata-Version: 2.1
Name: lahman
Version: 0.0.1
Summary: Data package for the Lahman database
Home-page: https://github.com/machow/lahman-py
Author: Michael Chow
Author-email: mc_al_github@fastmail.com
License: MIT
Keywords: data,baseball
Platform: UNKNOWN
Classifier: Programming Language :: Python :: 3.8
Classifier: Programming Language :: Python :: 3.9
Classifier: Programming Language :: Python :: 3.10
Requires-Python: >=3.7
License-File: LICENSE
Requires-Dist: pandas
Requires-Dist: importlib-metadata ; python_version < "3.8"
Requires-Dist: importlib-resources ; python_version < "3.9"
Provides-Extra: dev
Requires-Dist: requests ; extra == 'dev'
Requires-Dist: pydata-sphinx-theme ; extra == 'dev'
Requires-Dist: pytest ; extra == 'dev'
Requires-Dist: pytest-dotenv ; extra == 'dev'
